{
  "lastUpdated": "2026-03-05T22:18:08.487Z",
  "data": [
    {
      "contract": "Apr 2026",
      "symbol": "NGJ26.NYM",
      "month": 4,
      "year": 2026,
      "cmeCode": "NGJ26",
      "price": 2.999,
      "open": 2.937,
      "high": 3.046,
      "low": 2.92,
      "volume": 140492,
      "lastUpdate": "2026-03-05T21:59:59.000Z",
      "expiryDate": "2026-03-27"
    },
    {
      "contract": "May 2026",
      "symbol": "NGK26.NYM",
      "month": 5,
      "year": 2026,
      "cmeCode": "NGK26",
      "price": 3.014,
      "open": 2.956,
      "high": 3.068,
      "low": 2.941,
      "volume": 82169,
      "lastUpdate": "2026-03-05T21:59:45.000Z",
      "expiryDate": "2026-04-28"
    },
    {
      "contract": "Jun 2026",
      "symbol": "NGM26.NYM",
      "month": 6,
      "year": 2026,
      "cmeCode": "NGM26",
      "price": 3.176,
      "open": 3.128,
      "high": 3.251,
      "low": 3.127,
      "volume": 47388,
      "lastUpdate": "2026-03-05T21:59:57.000Z",
      "expiryDate": "2026-05-27"
    },
    {
      "contract": "Jul 2026",
      "symbol": "NGN26.NYM",
      "month": 7,
      "year": 2026,
      "cmeCode": "NGN26",
      "price": 3.473,
      "open": 3.411,
      "high": 3.545,
      "low": 3.409,
      "volume": 38702,
      "lastUpdate": "2026-03-05T21:59:59.000Z",
      "expiryDate": "2026-06-26"
    },
    {
      "contract": "Aug 2026",
      "symbol": "NGQ26.NYM",
      "month": 8,
      "year": 2026,
      "cmeCode": "NGQ26",
      "price": 3.556,
      "open": 3.501,
      "high": 3.624,
      "low": 3.488,
      "volume": 21070,
      "lastUpdate": "2026-03-05T21:59:59.000Z",
      "expiryDate": "2026-07-29"
    },
    {
      "contract": "Sep 2026",
      "symbol": "NGU26.NYM",
      "month": 9,
      "year": 2026,
      "cmeCode": "NGU26",
      "price": 3.542,
      "open": 3.478,
      "high": 3.61,
      "low": 3.473,
      "volume": 31187,
      "lastUpdate": "2026-03-05T21:59:59.000Z",
      "expiryDate": "2026-08-27"
    },
    {
      "contract": "Oct 2026",
      "symbol": "NGV26.NYM",
      "month": 10,
      "year": 2026,
      "cmeCode": "NGV26",
      "price": 3.611,
      "open": 3.538,
      "high": 3.675,
      "low": 3.533,
      "volume": 52149,
      "lastUpdate": "2026-03-05T21:59:59.000Z",
      "expiryDate": "2026-09-28"
    },
    {
      "contract": "Nov 2026",
      "symbol": "NGX26.NYM",
      "month": 11,
      "year": 2026,
      "cmeCode": "NGX26",
      "price": 3.908,
      "open": 3.822,
      "high": 3.974,
      "low": 3.816,
      "volume": 20787,
      "lastUpdate": "2026-03-05T21:59:55.000Z",
      "expiryDate": "2026-10-28"
    },
    {
      "contract": "Dec 2026",
      "symbol": "NGZ26.NYM",
      "month": 12,
      "year": 2026,
      "cmeCode": "NGZ26",
      "price": 4.689,
      "open": 4.533,
      "high": 4.759,
      "low": 4.515,
      "volume": 19114,
      "lastUpdate": "2026-03-05T21:59:56.000Z",
      "expiryDate": "2026-11-25"
    },
    {
      "contract": "Jan 2027",
      "symbol": "NGF27.NYM",
      "month": 1,
      "year": 2027,
      "cmeCode": "NGF27",
      "price": 5.116,
      "open": 4.922,
      "high": 5.171,
      "low": 4.907,
      "volume": 37686,
      "lastUpdate": "2026-03-05T21:59:59.000Z",
      "expiryDate": "2026-12-29"
    },
    {
      "contract": "Feb 2027",
      "symbol": "NGG27.NYM",
      "month": 2,
      "year": 2027,
      "cmeCode": "NGG27",
      "price": 4.55,
      "open": 4.401,
      "high": 4.595,
      "low": 4.398,
      "volume": 12856,
      "lastUpdate": "2026-03-05T21:59:58.000Z",
      "expiryDate": "2027-01-27"
    },
    {
      "contract": "Mar 2027",
      "symbol": "NGH27.NYM",
      "month": 3,
      "year": 2027,
      "cmeCode": "NGH27",
      "price": 3.608,
      "open": 3.576,
      "high": 3.661,
      "low": 3.545,
      "volume": 15078,
      "lastUpdate": "2026-03-05T21:54:51.000Z",
      "expiryDate": "2027-02-24"
    },
    {
      "contract": "Apr 2027",
      "symbol": "NGJ27.NYM",
      "month": 4,
      "year": 2027,
      "cmeCode": "NGJ27",
      "price": 3.217,
      "open": 3.222,
      "high": 3.253,
      "low": 3.195,
      "volume": 15574,
      "lastUpdate": "2026-03-05T21:57:54.000Z",
      "expiryDate": "2027-03-29"
    },
    {
      "contract": "May 2027",
      "symbol": "NGK27.NYM",
      "month": 5,
      "year": 2027,
      "cmeCode": "NGK27",
      "price": 3.201,
      "open": 3.223,
      "high": 3.231,
      "low": 3.178,
      "volume": 3533,
      "lastUpdate": "2026-03-05T21:57:48.000Z",
      "expiryDate": "2027-04-28"
    },
    {
      "contract": "Jun 2027",
      "symbol": "NGM27.NYM",
      "month": 6,
      "year": 2027,
      "cmeCode": "NGM27",
      "price": 3.332,
      "open": 3.352,
      "high": 3.37,
      "low": 3.321,
      "volume": 2208,
      "lastUpdate": "2026-03-05T20:54:36.000Z",
      "expiryDate": "2027-05-26"
    },
    {
      "contract": "Jul 2027",
      "symbol": "NGN27.NYM",
      "month": 7,
      "year": 2027,
      "cmeCode": "NGN27",
      "price": 3.522,
      "open": 3.536,
      "high": 3.546,
      "low": 3.506,
      "volume": 2760,
      "lastUpdate": "2026-03-05T21:54:51.000Z",
      "expiryDate": "2027-06-28"
    },
    {
      "contract": "Aug 2027",
      "symbol": "NGQ27.NYM",
      "month": 8,
      "year": 2027,
      "cmeCode": "NGQ27",
      "price": 3.571,
      "open": 3.586,
      "high": 3.592,
      "low": 3.556,
      "volume": 1713,
      "lastUpdate": "2026-03-05T21:54:51.000Z",
      "expiryDate": "2027-07-28"
    },
    {
      "contract": "Sep 2027",
      "symbol": "NGU27.NYM",
      "month": 9,
      "year": 2027,
      "cmeCode": "NGU27",
      "price": 3.549,
      "open": 3.551,
      "high": 3.572,
      "low": 3.538,
      "volume": 1362,
      "lastUpdate": "2026-03-05T21:55:58.000Z",
      "expiryDate": "2027-08-27"
    },
    {
      "contract": "Oct 2027",
      "symbol": "NGV27.NYM",
      "month": 10,
      "year": 2027,
      "cmeCode": "NGV27",
      "price": 3.621,
      "open": 3.644,
      "high": 3.647,
      "low": 3.602,
      "volume": 4842,
      "lastUpdate": "2026-03-05T21:55:58.000Z",
      "expiryDate": "2027-09-28"
    },
    {
      "contract": "Nov 2027",
      "symbol": "NGX27.NYM",
      "month": 11,
      "year": 2027,
      "cmeCode": "NGX27",
      "price": 3.833,
      "open": 3.858,
      "high": 3.879,
      "low": 3.824,
      "volume": 2666,
      "lastUpdate": "2026-03-05T21:36:02.000Z",
      "expiryDate": "2027-10-27"
    },
    {
      "contract": "Dec 2027",
      "symbol": "NGZ27.NYM",
      "month": 12,
      "year": 2027,
      "cmeCode": "NGZ27",
      "price": 4.51,
      "open": 4.492,
      "high": 4.54,
      "low": 4.471,
      "volume": 2352,
      "lastUpdate": "2026-03-05T21:55:42.000Z",
      "expiryDate": "2027-11-26"
    },
    {
      "contract": "Jan 2028",
      "symbol": "NGF28.NYM",
      "month": 1,
      "year": 2028,
      "cmeCode": "NGF28",
      "price": 4.93,
      "open": 4.873,
      "high": 4.938,
      "low": 4.865,
      "volume": 2456,
      "lastUpdate": "2026-03-05T21:59:59.000Z",
      "expiryDate": "2027-12-29"
    },
    {
      "contract": "Feb 2028",
      "symbol": "NGG28.NYM",
      "month": 2,
      "year": 2028,
      "cmeCode": "NGG28",
      "price": 4.284,
      "open": 4.267,
      "high": 4.31,
      "low": 4.262,
      "volume": 1101,
      "lastUpdate": "2026-03-05T21:59:59.000Z",
      "expiryDate": "2028-01-27"
    },
    {
      "contract": "Mar 2028",
      "symbol": "NGH28.NYM",
      "month": 3,
      "year": 2028,
      "cmeCode": "NGH28",
      "price": 3.447,
      "open": 3.479,
      "high": 3.502,
      "low": 3.417,
      "volume": 1215,
      "lastUpdate": "2026-03-05T21:11:13.000Z",
      "expiryDate": "2028-02-25"
    },
    {
      "contract": "Apr 2028",
      "symbol": "NGJ28.NYM",
      "month": 4,
      "year": 2028,
      "cmeCode": "NGJ28",
      "price": 3.105,
      "open": 3.12,
      "high": 3.132,
      "low": 3.1,
      "volume": 1056,
      "lastUpdate": "2026-03-05T18:40:22.000Z",
      "expiryDate": "2028-03-29"
    },
    {
      "contract": "May 2028",
      "symbol": "NGK28.NYM",
      "month": 5,
      "year": 2028,
      "cmeCode": "NGK28",
      "price": 3.1,
      "open": 3.12,
      "high": 3.12,
      "low": 3.1,
      "volume": 413,
      "lastUpdate": "2026-03-05T19:08:37.000Z",
      "expiryDate": "2028-04-26"
    },
    {
      "contract": "Jun 2028",
      "symbol": "NGM28.NYM",
      "month": 6,
      "year": 2028,
      "cmeCode": "NGM28",
      "price": 3.26,
      "open": 3.26,
      "high": 3.26,
      "low": 3.26,
      "volume": 177,
      "lastUpdate": "2026-03-05T13:20:50.000Z",
      "expiryDate": "2028-05-26"
    },
    {
      "contract": "Jul 2028",
      "symbol": "NGN28.NYM",
      "month": 7,
      "year": 2028,
      "cmeCode": "NGN28",
      "price": 3.41,
      "open": 3.41,
      "high": 3.41,
      "low": 3.41,
      "volume": 118,
      "lastUpdate": "2026-03-04T17:13:32.000Z",
      "expiryDate": "2028-06-28"
    },
    {
      "contract": "Aug 2028",
      "symbol": "NGQ28.NYM",
      "month": 8,
      "year": 2028,
      "cmeCode": "NGQ28",
      "price": 3.471,
      "open": 3.471,
      "high": 3.471,
      "low": 3.471,
      "volume": 49,
      "lastUpdate": "2026-03-03T20:58:47.000Z",
      "expiryDate": "2028-07-27"
    },
    {
      "contract": "Sep 2028",
      "symbol": "NGU28.NYM",
      "month": 9,
      "year": 2028,
      "cmeCode": "NGU28",
      "price": 3.455,
      "open": 3.455,
      "high": 3.455,
      "low": 3.455,
      "volume": 43,
      "lastUpdate": "2026-03-05T14:53:38.000Z",
      "expiryDate": "2028-08-29"
    },
    {
      "contract": "Oct 2028",
      "symbol": "NGV28.NYM",
      "month": 10,
      "year": 2028,
      "cmeCode": "NGV28",
      "price": 3.537,
      "open": 3.547,
      "high": 3.547,
      "low": 3.537,
      "volume": 71,
      "lastUpdate": "2026-03-05T19:26:14.000Z",
      "expiryDate": "2028-09-27"
    },
    {
      "contract": "Nov 2028",
      "symbol": "NGX28.NYM",
      "month": 11,
      "year": 2028,
      "cmeCode": "NGX28",
      "price": 3.769,
      "open": 3.769,
      "high": 3.769,
      "low": 3.769,
      "volume": 47,
      "lastUpdate": "2026-03-04T16:13:13.000Z",
      "expiryDate": "2028-10-27"
    },
    {
      "contract": "Dec 2028",
      "symbol": "NGZ28.NYM",
      "month": 12,
      "year": 2028,
      "cmeCode": "NGZ28",
      "price": 4.39,
      "open": 4.39,
      "high": 4.39,
      "low": 4.39,
      "volume": 47,
      "lastUpdate": "2026-03-05T13:26:26.000Z",
      "expiryDate": "2028-11-28"
    },
    {
      "contract": "Jan 2029",
      "symbol": "NGF29.NYM",
      "month": 1,
      "year": 2029,
      "cmeCode": "NGF29",
      "price": 4.73,
      "open": 4.73,
      "high": 4.73,
      "low": 4.73,
      "volume": 46,
      "lastUpdate": "2026-03-05T13:22:59.000Z",
      "expiryDate": "2028-12-27"
    },
    {
      "contract": "Feb 2029",
      "symbol": "NGG29.NYM",
      "month": 2,
      "year": 2029,
      "cmeCode": "NGG29",
      "price": 4.12,
      "open": 4.12,
      "high": 4.12,
      "low": 4.12,
      "volume": 15,
      "lastUpdate": "2026-03-01T23:20:06.000Z",
      "expiryDate": "2029-01-29"
    }
  ]
}