{
  "lastUpdated": "2026-02-24T22:20:08.911Z",
  "data": [
    {
      "contract": "Mar 2026",
      "symbol": "NGH26.NYM",
      "month": 3,
      "year": 2026,
      "cmeCode": "NGH26",
      "price": 2.922,
      "open": 2.981,
      "high": 3.014,
      "low": 2.905,
      "volume": 49138,
      "lastUpdate": "2026-02-24T21:57:51.000Z",
      "expiryDate": "2026-02-25"
    },
    {
      "contract": "Apr 2026",
      "symbol": "NGJ26.NYM",
      "month": 4,
      "year": 2026,
      "cmeCode": "NGJ26",
      "price": 2.835,
      "open": 2.918,
      "high": 2.934,
      "low": 2.826,
      "volume": 126095,
      "lastUpdate": "2026-02-24T21:59:59.000Z",
      "expiryDate": "2026-03-27"
    },
    {
      "contract": "May 2026",
      "symbol": "NGK26.NYM",
      "month": 5,
      "year": 2026,
      "cmeCode": "NGK26",
      "price": 2.858,
      "open": 2.942,
      "high": 2.956,
      "low": 2.849,
      "volume": 55531,
      "lastUpdate": "2026-02-24T21:59:59.000Z",
      "expiryDate": "2026-04-28"
    },
    {
      "contract": "Jun 2026",
      "symbol": "NGM26.NYM",
      "month": 6,
      "year": 2026,
      "cmeCode": "NGM26",
      "price": 3.038,
      "open": 3.122,
      "high": 3.133,
      "low": 3.028,
      "volume": 26256,
      "lastUpdate": "2026-02-24T21:59:57.000Z",
      "expiryDate": "2026-05-27"
    },
    {
      "contract": "Jul 2026",
      "symbol": "NGN26.NYM",
      "month": 7,
      "year": 2026,
      "cmeCode": "NGN26",
      "price": 3.325,
      "open": 3.394,
      "high": 3.403,
      "low": 3.314,
      "volume": 26332,
      "lastUpdate": "2026-02-24T21:59:57.000Z",
      "expiryDate": "2026-06-26"
    },
    {
      "contract": "Aug 2026",
      "symbol": "NGQ26.NYM",
      "month": 8,
      "year": 2026,
      "cmeCode": "NGQ26",
      "price": 3.404,
      "open": 3.473,
      "high": 3.482,
      "low": 3.396,
      "volume": 11799,
      "lastUpdate": "2026-02-24T21:58:27.000Z",
      "expiryDate": "2026-07-29"
    },
    {
      "contract": "Sep 2026",
      "symbol": "NGU26.NYM",
      "month": 9,
      "year": 2026,
      "cmeCode": "NGU26",
      "price": 3.386,
      "open": 3.466,
      "high": 3.467,
      "low": 3.383,
      "volume": 15154,
      "lastUpdate": "2026-02-24T21:59:18.000Z",
      "expiryDate": "2026-08-27"
    },
    {
      "contract": "Oct 2026",
      "symbol": "NGV26.NYM",
      "month": 10,
      "year": 2026,
      "cmeCode": "NGV26",
      "price": 3.444,
      "open": 3.522,
      "high": 3.522,
      "low": 3.439,
      "volume": 22062,
      "lastUpdate": "2026-02-24T21:59:45.000Z",
      "expiryDate": "2026-09-28"
    },
    {
      "contract": "Nov 2026",
      "symbol": "NGX26.NYM",
      "month": 11,
      "year": 2026,
      "cmeCode": "NGX26",
      "price": 3.708,
      "open": 3.779,
      "high": 3.779,
      "low": 3.702,
      "volume": 11289,
      "lastUpdate": "2026-02-24T21:48:55.000Z",
      "expiryDate": "2026-10-28"
    },
    {
      "contract": "Dec 2026",
      "symbol": "NGZ26.NYM",
      "month": 12,
      "year": 2026,
      "cmeCode": "NGZ26",
      "price": 4.313,
      "open": 4.397,
      "high": 4.397,
      "low": 4.313,
      "volume": 6815,
      "lastUpdate": "2026-02-24T21:58:55.000Z",
      "expiryDate": "2026-11-25"
    },
    {
      "contract": "Jan 2027",
      "symbol": "NGF27.NYM",
      "month": 1,
      "year": 2027,
      "cmeCode": "NGF27",
      "price": 4.682,
      "open": 4.759,
      "high": 4.759,
      "low": 4.676,
      "volume": 11197,
      "lastUpdate": "2026-02-24T21:59:50.000Z",
      "expiryDate": "2026-12-29"
    },
    {
      "contract": "Feb 2027",
      "symbol": "NGG27.NYM",
      "month": 2,
      "year": 2027,
      "cmeCode": "NGG27",
      "price": 4.182,
      "open": 4.235,
      "high": 4.24,
      "low": 4.177,
      "volume": 5169,
      "lastUpdate": "2026-02-24T21:59:50.000Z",
      "expiryDate": "2027-01-27"
    },
    {
      "contract": "Mar 2027",
      "symbol": "NGH27.NYM",
      "month": 3,
      "year": 2027,
      "cmeCode": "NGH27",
      "price": 3.451,
      "open": 3.493,
      "high": 3.5,
      "low": 3.45,
      "volume": 8425,
      "lastUpdate": "2026-02-24T21:59:18.000Z",
      "expiryDate": "2027-02-24"
    },
    {
      "contract": "Apr 2027",
      "symbol": "NGJ27.NYM",
      "month": 4,
      "year": 2027,
      "cmeCode": "NGJ27",
      "price": 3.171,
      "open": 3.189,
      "high": 3.202,
      "low": 3.163,
      "volume": 6402,
      "lastUpdate": "2026-02-24T21:11:34.000Z",
      "expiryDate": "2027-03-29"
    },
    {
      "contract": "May 2027",
      "symbol": "NGK27.NYM",
      "month": 5,
      "year": 2027,
      "cmeCode": "NGK27",
      "price": 3.166,
      "open": 3.186,
      "high": 3.194,
      "low": 3.158,
      "volume": 1775,
      "lastUpdate": "2026-02-24T20:49:32.000Z",
      "expiryDate": "2027-04-28"
    },
    {
      "contract": "Jun 2027",
      "symbol": "NGM27.NYM",
      "month": 6,
      "year": 2027,
      "cmeCode": "NGM27",
      "price": 3.308,
      "open": 3.318,
      "high": 3.337,
      "low": 3.299,
      "volume": 1032,
      "lastUpdate": "2026-02-24T20:24:02.000Z",
      "expiryDate": "2027-05-26"
    },
    {
      "contract": "Jul 2027",
      "symbol": "NGN27.NYM",
      "month": 7,
      "year": 2027,
      "cmeCode": "NGN27",
      "price": 3.504,
      "open": 3.497,
      "high": 3.523,
      "low": 3.491,
      "volume": 1020,
      "lastUpdate": "2026-02-24T21:06:04.000Z",
      "expiryDate": "2027-06-28"
    },
    {
      "contract": "Aug 2027",
      "symbol": "NGQ27.NYM",
      "month": 8,
      "year": 2027,
      "cmeCode": "NGQ27",
      "price": 3.558,
      "open": 3.558,
      "high": 3.578,
      "low": 3.546,
      "volume": 861,
      "lastUpdate": "2026-02-24T21:06:04.000Z",
      "expiryDate": "2027-07-28"
    },
    {
      "contract": "Sep 2027",
      "symbol": "NGU27.NYM",
      "month": 9,
      "year": 2027,
      "cmeCode": "NGU27",
      "price": 3.532,
      "open": 3.54,
      "high": 3.565,
      "low": 3.525,
      "volume": 910,
      "lastUpdate": "2026-02-24T21:43:50.000Z",
      "expiryDate": "2027-08-27"
    },
    {
      "contract": "Oct 2027",
      "symbol": "NGV27.NYM",
      "month": 10,
      "year": 2027,
      "cmeCode": "NGV27",
      "price": 3.596,
      "open": 3.604,
      "high": 3.622,
      "low": 3.589,
      "volume": 1859,
      "lastUpdate": "2026-02-24T21:43:34.000Z",
      "expiryDate": "2027-09-28"
    },
    {
      "contract": "Nov 2027",
      "symbol": "NGX27.NYM",
      "month": 11,
      "year": 2027,
      "cmeCode": "NGX27",
      "price": 3.83,
      "open": 3.845,
      "high": 3.852,
      "low": 3.82,
      "volume": 931,
      "lastUpdate": "2026-02-24T21:43:34.000Z",
      "expiryDate": "2027-10-27"
    },
    {
      "contract": "Dec 2027",
      "symbol": "NGZ27.NYM",
      "month": 12,
      "year": 2027,
      "cmeCode": "NGZ27",
      "price": 4.425,
      "open": 4.446,
      "high": 4.45,
      "low": 4.414,
      "volume": 552,
      "lastUpdate": "2026-02-24T21:44:22.000Z",
      "expiryDate": "2027-11-26"
    },
    {
      "contract": "Jan 2028",
      "symbol": "NGF28.NYM",
      "month": 1,
      "year": 2028,
      "cmeCode": "NGF28",
      "price": 4.781,
      "open": 4.806,
      "high": 4.809,
      "low": 4.77,
      "volume": 519,
      "lastUpdate": "2026-02-24T21:44:22.000Z",
      "expiryDate": "2027-12-29"
    },
    {
      "contract": "Feb 2028",
      "symbol": "NGG28.NYM",
      "month": 2,
      "year": 2028,
      "cmeCode": "NGG28",
      "price": 4.21,
      "open": 4.213,
      "high": 4.226,
      "low": 4.206,
      "volume": 403,
      "lastUpdate": "2026-02-24T17:01:31.000Z",
      "expiryDate": "2028-01-27"
    },
    {
      "contract": "Mar 2028",
      "symbol": "NGH28.NYM",
      "month": 3,
      "year": 2028,
      "cmeCode": "NGH28",
      "price": 3.47,
      "open": 3.461,
      "high": 3.47,
      "low": 3.461,
      "volume": 298,
      "lastUpdate": "2026-02-24T15:13:40.000Z",
      "expiryDate": "2028-02-25"
    },
    {
      "contract": "Apr 2028",
      "symbol": "NGJ28.NYM",
      "month": 4,
      "year": 2028,
      "cmeCode": "NGJ28",
      "price": 3.11,
      "open": 3.109,
      "high": 3.11,
      "low": 3.093,
      "volume": 172,
      "lastUpdate": "2026-02-24T19:09:41.000Z",
      "expiryDate": "2028-03-29"
    },
    {
      "contract": "May 2028",
      "symbol": "NGK28.NYM",
      "month": 5,
      "year": 2028,
      "cmeCode": "NGK28",
      "price": 3.15,
      "open": 3.108,
      "high": 3.15,
      "low": 3.108,
      "volume": 8,
      "lastUpdate": "2026-02-20T20:31:29.000Z",
      "expiryDate": "2028-04-26"
    },
    {
      "contract": "Jun 2028",
      "symbol": "NGM28.NYM",
      "month": 6,
      "year": 2028,
      "cmeCode": "NGM28",
      "price": 3.243,
      "open": 3.243,
      "high": 3.243,
      "low": 3.243,
      "volume": 22,
      "lastUpdate": "2026-02-19T14:54:05.000Z",
      "expiryDate": "2028-05-26"
    },
    {
      "contract": "Jul 2028",
      "symbol": "NGN28.NYM",
      "month": 7,
      "year": 2028,
      "cmeCode": "NGN28",
      "price": 3.395,
      "open": 3.419,
      "high": 3.419,
      "low": 3.395,
      "volume": 30,
      "lastUpdate": "2026-02-19T20:09:30.000Z",
      "expiryDate": "2028-06-28"
    },
    {
      "contract": "Aug 2028",
      "symbol": "NGQ28.NYM",
      "month": 8,
      "year": 2028,
      "cmeCode": "NGQ28",
      "price": 3.462,
      "open": 3.482,
      "high": 3.482,
      "low": 3.462,
      "volume": 38,
      "lastUpdate": "2026-02-24T17:45:55.000Z",
      "expiryDate": "2028-07-27"
    },
    {
      "contract": "Sep 2028",
      "symbol": "NGU28.NYM",
      "month": 9,
      "year": 2028,
      "cmeCode": "NGU28",
      "price": 3.465,
      "open": 3.465,
      "high": 3.465,
      "low": 3.465,
      "volume": 37,
      "lastUpdate": "2026-02-20T19:43:02.000Z",
      "expiryDate": "2028-08-29"
    },
    {
      "contract": "Oct 2028",
      "symbol": "NGV28.NYM",
      "month": 10,
      "year": 2028,
      "cmeCode": "NGV28",
      "price": 3.516,
      "open": 3.526,
      "high": 3.526,
      "low": 3.516,
      "volume": 180,
      "lastUpdate": "2026-02-24T15:28:38.000Z",
      "expiryDate": "2028-09-27"
    },
    {
      "contract": "Nov 2028",
      "symbol": "NGX28.NYM",
      "month": 11,
      "year": 2028,
      "cmeCode": "NGX28",
      "price": 3.769,
      "open": 3.769,
      "high": 3.769,
      "low": 3.769,
      "volume": 161,
      "lastUpdate": "2026-02-24T14:41:45.000Z",
      "expiryDate": "2028-10-27"
    },
    {
      "contract": "Dec 2028",
      "symbol": "NGZ28.NYM",
      "month": 12,
      "year": 2028,
      "cmeCode": "NGZ28",
      "price": 4.337,
      "open": 4.337,
      "high": 4.337,
      "low": 4.337,
      "volume": 20,
      "lastUpdate": "2026-02-24T14:42:04.000Z",
      "expiryDate": "2028-11-28"
    },
    {
      "contract": "Jan 2029",
      "symbol": "NGF29.NYM",
      "month": 1,
      "year": 2029,
      "cmeCode": "NGF29",
      "price": 4.671,
      "open": 4.671,
      "high": 4.671,
      "low": 4.671,
      "volume": 67,
      "lastUpdate": "2026-02-24T15:14:37.000Z",
      "expiryDate": "2028-12-27"
    }
  ]
}